{"workout_id":"0220513f-bc72-41e3-a8a9-ce12b234ed70","completed_at":"2020-11-05T15:47:25.973Z","average_heart_rate":105,"max_heart_rate":137,"id":"f9fb516e-33e9-4e5e-a188-27c43109516b","difficulty":0.42167255,"set_summaries":[{"id":"02aff719-98e3-4e85-a2dd-3f00bb9c9979","set":{"reps":0,"weight":0,"id":"594b9c69-2d50-49cb-a24e-db74be19c282","distance":0,"estimated_duration":30,"position":0,"exercise":{"is_two_dumbbells":false,"type":"","is_alternating":true,"id":"1efc2bbb-5ce6-4611-9774-acfff7218378","side":"","movement_patterns":"Dynamic Flexibility","name":"Spiderman Stretch","description":"Start in a high plank and lunge your right leg forward keeping both hands to the left of your right leg. Keeping your right leg at ninety degrees, hold, bring your foot back and repeat on the other side","is_weight":false,"is_duration":true,"is_reps":true},"is_two_dumbbells":false,"intensity":"","duration":30,"type":"duration"},"set_id":"594b9c69-2d50-49cb-a24e-db74be19c282","started_at":"2020-11-05T14:55:35.979Z","time_spent_active":30,"summary_id":"f9fb516e-33e9-4e5e-a188-27c43109516b","completed_at":"2020-11-05T14:56:05.442Z"},{"completed_at":"2020-11-05T15:35:57.481Z","started_at":"2020-11-05T15:35:38.688Z","id":"03c6035f-958e-4aba-9505-d13022662f74","set_id":"79e5b424-1721-4c59-b144-de0b36910823","set":{"exercise":{"id":"01f5a2bb-ecf7-4168-92b3-35bd78592e26","is_alternating":true,"is_weight":false,"type":"","name":"High Plank Bird Dog","is_two_dumbbells":false,"movement_patterns":"Anti-Extension,Anti-Rotation","side":"","is_reps":true,"is_duration":true,"muscle_groups":"Core,Shoulders,Obliques"},"type":"reps","distance":0,"intensity":"reps_slow","position":4,"estimated_duration":55,"is_two_dumbbells":false,"reps":5,"duration":30,"id":"79e5b424-1721-4c59-b144-de0b36910823","weight":0},"time_spent_active":19,"summary_id":"f9fb516e-33e9-4e5e-a188-27c43109516b"},{"time_spent_active":30,"set_id":"5044cca8-4f5a-4ef0-9020-957a84a7a5c2","completed_at":"2020-11-05T15:18:44.822Z","started_at":"2020-11-05T15:18:15.355Z","summary_id":"f9fb516e-33e9-4e5e-a188-27c43109516b","set":{"exercise":{"is_duration":true,"is_weight":false,"side":"","description":"Use this time to catch your breath. It will help you get more out of what's next","is_reps":false,"is_alternating":false,"name":"Recover","is_two_dumbbells":false,"id":"9b983f5f-e229-4d46-9258-e11e430d3a54","type":"rest"},"type":"duration","distance":0,"duration":30,"weight":0,"reps":0,"estimated_duration":30,"is_two_dumbbells":false,"id":"5044cca8-4f5a-4ef0-9020-957a84a7a5c2","position":1},"id":"071ecb04-1e73-455d-bc65-c3ea3855aec8"},{"set_id":"7ba02b4f-8024-4b4d-ac53-2712bf6f48ec","time_spent_active":30,"summary_id":"f9fb516e-33e9-4e5e-a188-27c43109516b","started_at":"2020-11-05T14:59:53.310Z","id":"0a4f7b5f-e3a4-49a4-9009-e1ad649c7f89","set":{"estimated_duration":30,"weight":0,"type":"duration","position":7,"duration":30,"reps":0,"intensity":"","exercise":{"id":"14f52c4a-174b-4514-a1b0-bf98072a4a60","movement_patterns":"Dynamic Flexibility","side":"","is_alternating":true,"description":"Standing tall with your weight on one leg, pull your heel toward your glute, pause and release.  Switch legs","is_duration":true,"is_weight":false,"name":"Dynamic Quadriceps Stretch","muscle_groups":"Quads","is_reps":true,"is_two_dumbbells":false,"type":""},"id":"7ba02b4f-8024-4b4d-ac53-2712bf6f48ec","is_two_dumbbells":false,"distance":0},"completed_at":"2020-11-05T15:00:22.771Z"},{"time_spent_active":30,"started_at":"2020-11-05T14:56:47.790Z","set_id":"36ab7d5f-5d31-4d0c-9aa5-9a487f26d25a","completed_at":"2020-11-05T14:57:17.254Z","summary_id":"f9fb516e-33e9-4e5e-a188-27c43109516b","id":"14b81203-3c5a-4c12-b612-eb42db0ff581","set":{"type":"duration","weight":0,"reps":0,"exercise":{"type":"","is_alternating":false,"is_two_dumbbells":false,"id":"0d8ba53e-b646-4f89-9cdc-7acbe3385225","is_duration":true,"description":"Starting in a childs pose sitting back on your heels, reach your left arm and press the palm into the floor.  Right hand behind your head, rotate right, stretching your back and chest.","is_reps":true,"is_weight":false,"movement_patterns":"Mobility","name":"Prayer Stretch","side":"right_arm"},"is_two_dumbbells":false,"estimated_duration":30,"id":"36ab7d5f-5d31-4d0c-9aa5-9a487f26d25a","position":2,"duration":30,"distance":0}},{"summary_id":"f9fb516e-33e9-4e5e-a188-27c43109516b","started_at":"2020-11-05T15:44:23.501Z","id":"17a938d6-2a15-4ea6-add1-0c2db8a05cf0","completed_at":"2020-11-05T15:44:52.963Z","set_id":"8c96f861-4d61-40b6-9f79-0811f76c3884","time_spent_active":30,"set":{"weight":0,"position":7,"intensity":"","type":"duration","is_two_dumbbells":false,"distance":0,"reps":0,"estimated_duration":30,"duration":30,"id":"8c96f861-4d61-40b6-9f79-0811f76c3884","exercise":{"muscle_groups":"Rectus Abdominis,Lower Back","is_reps":false,"id":"989a12f9-d9f4-4000-b61b-db5b5e84e42e","is_alternating":false,"side":"","is_weight":false,"name":"Cobra Pose","is_two_dumbbells":false,"movement_patterns":"Yoga,Stretch","type":"","is_duration":true}}},{"time_spent_active":30,"completed_at":"2020-11-05T15:41:15.646Z","set_id":"05de9e6f-cde0-4348-b357-ba33e7a40bc4","started_at":"2020-11-05T15:40:46.180Z","set":{"estimated_duration":30,"weight":0,"intensity":"","position":1,"exercise":{"is_two_dumbbells":false,"type":"","is_alternating":false,"movement_patterns":"Mobility","is_weight":false,"is_reps":false,"is_duration":true,"id":"79f9e0db-a261-46b7-8702-a8073dddd1d2","description":"Kneel on the floor with your left leg forward and right leg back.  With perfect posture, press your hips forward until your feel a stretch in the front of your right thigh.","muscle_groups":"Quads","name":"Kneeling Quadriceps Stretch","side":"right_leg"},"id":"05de9e6f-cde0-4348-b357-ba33e7a40bc4","duration":30,"is_two_dumbbells":false,"distance":0,"type":"duration","reps":0},"id":"1a15ae06-2ed5-477c-85f5-a91870904b16","summary_id":"f9fb516e-33e9-4e5e-a188-27c43109516b"},{"completed_at":"2020-11-05T15:32:32.901Z","started_at":"2020-11-05T15:32:03.440Z","set":{"is_two_dumbbells":false,"reps":0,"distance":0,"weight":0,"position":8,"estimated_duration":30,"id":"6fe7d3c8-36fc-4d6b-ae61-8ca020c2447f","type":"duration","duration":30,"exercise":{"description":"Use this time to catch your breath. It will help you get more out of what's next","is_alternating":false,"is_reps":false,"is_weight":false,"is_duration":true,"side":"","id":"9b983f5f-e229-4d46-9258-e11e430d3a54","is_two_dumbbells":false,"name":"Recover","type":"rest"}},"id":"1d375d7e-7348-478e-822b-1ffd0b1779b8","set_id":"6fe7d3c8-36fc-4d6b-ae61-8ca020c2447f","time_spent_active":30,"summary_id":"f9fb516e-33e9-4e5e-a188-27c43109516b"},{"summary_id":"f9fb516e-33e9-4e5e-a188-27c43109516b","started_at":"2020-11-05T15:43:13.791Z","id":"22b613ec-6616-4802-98f5-7715b781848d","time_spent_active":30,"set":{"id":"6920485d-5ea7-46c2-a599-bdc150dad7f9","type":"duration","exercise":{"muscle_groups":"Middle Back","name":"Crossbody Lat Stretch","is_duration":true,"is_alternating":false,"type":"","is_weight":false,"is_reps":false,"movement_patterns":"Mobility","side":"left_arm","id":"9f7b6b4b-b85b-4b22-8416-bcc195db128a","description":"In a child's pose sitting back on your heels, reach your left arm across your body and place the back of your palm on the floor.  Lock that hand down with your right hand, sit back and feel the stretch down your left side.","is_two_dumbbells":false},"position":5,"duration":30,"is_two_dumbbells":false,"distance":0,"weight":0,"intensity":"","reps":0,"estimated_duration":30},"set_id":"6920485d-5ea7-46c2-a599-bdc150dad7f9","completed_at":"2020-11-05T15:43:43.254Z"},{"set_id":"c75ff340-dc80-4cf9-88fe-d8a18c34530e","id":"27529073-d133-4eee-9b51-95cfae58c726","set":{"intensity":"","is_two_dumbbells":false,"id":"c75ff340-dc80-4cf9-88fe-d8a18c34530e","type":"reps","reps":12,"estimated_duration":26,"weight":0,"duration":20,"position":1,"exercise":{"is_reps":true,"is_weight":true,"type":"","movement_patterns":"Upper Pull","id":"0c380a97-5292-4e26-b238-9f4eb2f42db9","name":"Resistance Band Reverse Fly","is_alternating":false,"is_duration":true,"is_two_dumbbells":false,"description":"Stand with both feet on the center of the band, hip width apart. Bend at your hips about forty fives degrees. With your elbows slightly bent, pull the bands up and out to your sides","side":"","muscle_groups":"Middle Back"},"distance":0},"time_spent_active":38,"weight":0,"summary_id":"f9fb516e-33e9-4e5e-a188-27c43109516b","completed_at":"2020-11-05T15:28:13.867Z","started_at":"2020-11-05T15:27:36.200Z"},{"started_at":"2020-11-05T15:36:12.502Z","summary_id":"f9fb516e-33e9-4e5e-a188-27c43109516b","id":"34913e2d-520b-463b-bfff-0b6c88eba3f5","set_id":"0bbdf73b-1429-4a06-b892-ffbea24b835c","completed_at":"2020-11-05T15:37:32.091Z","set":{"type":"reps","distance":0,"id":"0bbdf73b-1429-4a06-b892-ffbea24b835c","estimated_duration":38,"weight":0,"duration":30,"is_two_dumbbells":false,"reps":12,"exercise":{"is_reps":true,"id":"90c7202e-231c-4830-af76-c89697d9158d","name":"Split Rope Chop","movement_patterns":"Core,Rotational","is_two_dumbbells":false,"is_duration":true,"side":"left_side","muscle_groups":"Abs,Obliques","description":"Start with your left knee down,, and right side facing the cable column.. Stay tall as you bring the rope in and across your body.. Finish with your arms straight,, and hands outside your left hip..","type":"","is_weight":true,"is_alternating":false},"position":5},"weight":0,"time_spent_active":80},{"time_spent_active":97,"id":"34c919ee-dbf3-4d64-bdd7-430dae232a3c","summary_id":"f9fb516e-33e9-4e5e-a188-27c43109516b","weight":0,"set":{"weight":0,"estimated_duration":38,"is_two_dumbbells":false,"distance":0,"position":1,"reps":12,"duration":30,"id":"c14db58a-5da4-41b0-baef-10756a8ed19e","exercise":{"muscle_groups":"Abs,Obliques","is_duration":true,"name":"Split Rope Chop","side":"left_side","type":"","is_alternating":false,"is_reps":true,"is_two_dumbbells":false,"id":"90c7202e-231c-4830-af76-c89697d9158d","description":"Start with your left knee down,, and right side facing the cable column.. Stay tall as you bring the rope in and across your body.. Finish with your arms straight,, and hands outside your left hip..","is_weight":true,"movement_patterns":"Core,Rotational"},"type":"reps"},"completed_at":"2020-11-05T15:34:58.539Z","set_id":"c14db58a-5da4-41b0-baef-10756a8ed19e","started_at":"2020-11-05T15:33:21.973Z"},{"weight":0,"time_spent_active":1,"summary_id":"f9fb516e-33e9-4e5e-a188-27c43109516b","started_at":"2020-11-05T15:39:57.747Z","set":{"is_two_dumbbells":false,"distance":0,"id":"86de61a3-ee2f-4dd6-bb29-687cc8efaa11","position":10,"type":"reps","exercise":{"description":"Start with your right knee down,, and left side facing the cable column.. Stay tall as you bring the rope in and across your body.. Finish with your arms straight,, and hands outside your right hip..","is_weight":true,"is_alternating":false,"is_reps":true,"name":"Split Rope Chop","movement_patterns":"Core,Rotational","type":"","is_duration":true,"is_two_dumbbells":false,"id":"f1b239c8-6f3d-4bcc-b562-2dcaa3a17c0a","muscle_groups":"Abs,Obliques","side":"right_side"},"duration":30,"reps":12,"weight":0,"estimated_duration":38},"id":"38aaa94e-a279-4258-99aa-f85e727854f3","completed_at":"2020-11-05T15:39:58.390Z","set_id":"86de61a3-ee2f-4dd6-bb29-687cc8efaa11"},{"set":{"position":6,"estimated_duration":38,"weight":0,"duration":30,"reps":12,"id":"5afd8607-d2d8-4b62-a1c1-5f4fbae93658","is_two_dumbbells":false,"exercise":{"name":"Split Rope Chop","type":"","is_weight":true,"id":"f1b239c8-6f3d-4bcc-b562-2dcaa3a17c0a","is_two_dumbbells":false,"muscle_groups":"Abs,Obliques","is_duration":true,"is_alternating":false,"side":"right_side","description":"Start with your right knee down,, and left side facing the cable column.. Stay tall as you bring the rope in and across your body.. Finish with your arms straight,, and hands outside your right hip..","is_reps":true,"movement_patterns":"Core,Rotational"},"type":"reps","distance":0},"set_id":"5afd8607-d2d8-4b62-a1c1-5f4fbae93658","started_at":"2020-11-05T15:37:32.889Z","summary_id":"f9fb516e-33e9-4e5e-a188-27c43109516b","id":"3e1f612e-72f9-44e2-9636-4799c44ce089","weight":0,"time_spent_active":1,"completed_at":"2020-11-05T15:37:33.640Z"},{"id":"415e2bf3-776a-4b06-a8bb-f8113e1be124","completed_at":"2020-11-05T14:58:33.065Z","time_spent_active":30,"summary_id":"f9fb516e-33e9-4e5e-a188-27c43109516b","started_at":"2020-11-05T14:58:03.600Z","set_id":"618287bb-72a6-4097-817b-8974eba37529","set":{"estimated_duration":30,"distance":0,"id":"618287bb-72a6-4097-817b-8974eba37529","duration":30,"weight":0,"exercise":{"is_weight":false,"description":"Stand on your left leg,, with your right knee and toe up.. Hinge your left hip back,, while reaching your right hand and foot,, to extend as long as you can.. Pull your hip forward to stand..","id":"bcfebd2c-0be6-4af2-8de5-8bd3a8d92110","is_duration":true,"muscle_groups":"Hamstrings","type":"","is_reps":true,"side":"left_leg","is_two_dumbbells":false,"is_alternating":false,"name":"Runner Touches","movement_patterns":"Dynamic Flexibility"},"position":4,"intensity":"","is_two_dumbbells":false,"reps":0,"type":"duration"}},{"completed_at":"2020-11-05T15:06:53.013Z","set_id":"4a39071b-34bd-4715-913b-a48524eea859","summary_id":"f9fb516e-33e9-4e5e-a188-27c43109516b","id":"429d8c40-9dbc-4d4e-bcd0-499edf0fe023","started_at":"2020-11-05T15:05:06.894Z","weight":35,"time_spent_active":107,"set":{"reps":12,"id":"4a39071b-34bd-4715-913b-a48524eea859","distance":0,"exercise":{"description":"Start in an athletic stance,, holding the rope with your hands facing each other.. Keep your elbows high,, and sqeeze them back,, to bring the rope towards your face.. Pause and return under contol..","is_reps":true,"id":"08df1103-cdd0-490a-8b9d-e44063f091ac","is_weight":true,"name":"Face Pull","is_two_dumbbells":false,"is_duration":true,"movement_patterns":"Scapular","muscle_groups":"Shoulders","is_alternating":false,"side":"","type":""},"weight":35,"duration":30,"type":"reps","position":2,"estimated_duration":33,"intensity":"weight_lb_35","is_two_dumbbells":false}},{"id":"43ecc095-bfc7-442f-ba49-74ea5f4f7bc7","set_id":"7e13d9fc-b4c7-4668-96f3-3522abd601a8","time_spent_active":30,"set":{"weight":0,"duration":30,"position":1,"estimated_duration":30,"reps":0,"id":"7e13d9fc-b4c7-4668-96f3-3522abd601a8","distance":0,"type":"duration","exercise":{"side":"left_arm","is_duration":true,"description":"Starting in a childs pose sitting back on your heels, reach your right arm and press the palm into the floor.  Left hand behind your head, rotate left, stretching your back and chest.","is_alternating":false,"movement_patterns":"Mobility","is_weight":false,"is_reps":true,"is_two_dumbbells":false,"name":"Prayer Stretch","id":"51c7a3a5-52a8-4b3e-849c-a34700a02bb5","type":""},"is_two_dumbbells":false},"summary_id":"f9fb516e-33e9-4e5e-a188-27c43109516b","started_at":"2020-11-05T14:56:13.890Z","completed_at":"2020-11-05T14:56:43.352Z"},{"completed_at":"2020-11-05T15:08:51.697Z","set_id":"bb1233bc-4f71-40dd-8e02-89d5d04dca60","time_spent_active":24,"summary_id":"f9fb516e-33e9-4e5e-a188-27c43109516b","id":"4768718e-0132-41d3-85a1-a509b58fb1b9","set":{"estimated_duration":27,"exercise":{"is_duration":true,"side":"left_arm","is_reps":true,"id":"305993c7-6825-4661-8ffb-40778b27327d","is_weight":true,"type":"","movement_patterns":"Upper Push","is_two_dumbbells":false,"is_alternating":false,"description":"Anchor the barbell in a corner. Place your left knee on the ground and hold the barbell with your left hand. Your right knee should be at ninety degrees. Lift the barbell up and out with your arm fully extended at the top. Slowly lower back down","name":"Landmine Shoulder Press","muscle_groups":"Shoulders"},"position":4,"type":"reps","duration":30,"reps":8,"id":"bb1233bc-4f71-40dd-8e02-89d5d04dca60","is_two_dumbbells":false,"intensity":"weight_lb_45","distance":0,"weight":45},"started_at":"2020-11-05T15:08:27.922Z","weight":45},{"set":{"id":"67f53287-2f37-4a6e-91f1-1c99433de71f","distance":0,"weight":0,"estimated_duration":30,"intensity":"","exercise":{"is_reps":true,"is_two_dumbbells":false,"name":"Runner Touches","description":"Stand on your right leg,, with your left knee and toe up.. Hinge your right hip back,, while reaching your left hand and foot,, to extend as long as you can.. Pull your hip forward to stand..","side":"right_leg","is_duration":true,"is_weight":false,"id":"ede43ab3-3488-4e99-aabf-917ec76ba81f","movement_patterns":"Dynamic Flexibility","muscle_groups":"Hamstrings","is_alternating":false,"type":""},"position":5,"reps":0,"is_two_dumbbells":false,"duration":30,"type":"duration"},"started_at":"2020-11-05T14:58:37.493Z","completed_at":"2020-11-05T14:59:06.958Z","set_id":"67f53287-2f37-4a6e-91f1-1c99433de71f","id":"485d9d02-a58b-4235-b6c9-a2029a1edf01","summary_id":"f9fb516e-33e9-4e5e-a188-27c43109516b","time_spent_active":30},{"set_id":"2ddd11f6-5fa4-4740-be13-af5f0ee612b5","started_at":"2020-11-05T15:46:17.218Z","completed_at":"2020-11-05T15:46:46.680Z","set":{"id":"2ddd11f6-5fa4-4740-be13-af5f0ee612b5","weight":0,"estimated_duration":30,"intensity":"","type":"duration","distance":0,"reps":0,"duration":30,"position":10,"exercise":{"description":"Put your left ankle against your right knee.  Use both hands to pull your legs back toward you.  Focus on rotating your left knee out to feel a greater stretch on the lateral hip.","is_alternating":false,"is_reps":false,"name":"Figure Four Stretch","muscle_groups":"Glutes","is_duration":true,"id":"c77b38db-defe-46d3-8dc3-a26ce196a134","is_weight":false,"movement_patterns":"Mobility","side":"left_leg","type":"","is_two_dumbbells":false},"is_two_dumbbells":false},"id":"49c426c8-32ca-453c-aa91-8429b2717bc4","summary_id":"f9fb516e-33e9-4e5e-a188-27c43109516b","time_spent_active":30},{"time_spent_active":61,"started_at":"2020-11-05T15:38:55.840Z","set":{"is_two_dumbbells":false,"distance":0,"duration":30,"reps":12,"type":"reps","weight":0,"id":"f6b73768-fa79-4225-95c1-f37d4061ef9a","exercise":{"type":"","is_weight":true,"is_alternating":false,"is_reps":true,"id":"90c7202e-231c-4830-af76-c89697d9158d","movement_patterns":"Core,Rotational","name":"Split Rope Chop","muscle_groups":"Abs,Obliques","is_duration":true,"side":"left_side","is_two_dumbbells":false,"description":"Start with your left knee down,, and right side facing the cable column.. Stay tall as you bring the rope in and across your body.. Finish with your arms straight,, and hands outside your left hip.."},"position":9,"estimated_duration":38},"set_id":"f6b73768-fa79-4225-95c1-f37d4061ef9a","weight":0,"completed_at":"2020-11-05T15:39:56.192Z","id":"4ef442fd-944c-4d56-b75d-66fd4cbc16aa","summary_id":"f9fb516e-33e9-4e5e-a188-27c43109516b"},{"set_id":"6fe8d99e-dbba-4ed2-8d66-e251088ef403","set":{"exercise":{"is_reps":true,"muscle_groups":"Shoulders","is_two_dumbbells":true,"description":"From a standing position with dumbbells in front of your hips and a slight bend in your elbow. Raise both dumbbells out to the side under control until they get to shoulder height.  Lower back to the starting position.","is_weight":true,"is_alternating":false,"movement_patterns":"Upper Push","side":"","type":"","name":"Dumbbell Lateral Shoulder Raises","is_duration":true,"id":"601770ea-0011-4c53-8e9f-65a5243ce724"},"id":"6fe8d99e-dbba-4ed2-8d66-e251088ef403","is_two_dumbbells":true,"intensity":"weight_lb:dumbbells_15","estimated_duration":28,"type":"reps","reps":10,"weight":15,"duration":30,"position":3,"distance":0},"started_at":"2020-11-05T15:28:53.802Z","id":"5458c52a-1d52-4d12-bfd0-8c70072f5cfa","completed_at":"2020-11-05T15:29:25.746Z","time_spent_active":32,"summary_id":"f9fb516e-33e9-4e5e-a188-27c43109516b","weight":15},{"set":{"exercise":{"type":"","side":"right_arm","is_alternating":false,"id":"f5cb60ae-4643-4896-bb7d-bd301805bcd7","is_duration":true,"is_reps":true,"is_two_dumbbells":false,"is_weight":true,"description":"Anchor the barbell in a corner. Place your right knee on the ground and hold the barbell with your right hand. Your left knee should be at ninety degrees. Lift the barbell up and out with your arm fully extended at the top. Slowly lower back down","muscle_groups":"Shoulders","movement_patterns":"Upper Push","name":"Landmine Shoulder Press"},"id":"52eb5fec-2abc-4074-af57-24f8beaf870c","reps":8,"is_two_dumbbells":false,"type":"reps","weight":45,"duration":30,"position":1,"distance":0,"estimated_duration":27,"intensity":"weight_lb_45"},"summary_id":"f9fb516e-33e9-4e5e-a188-27c43109516b","set_id":"52eb5fec-2abc-4074-af57-24f8beaf870c","weight":45,"time_spent_active":24,"started_at":"2020-11-05T15:04:27.978Z","completed_at":"2020-11-05T15:04:51.880Z","id":"58a08b60-d46a-4bfe-821b-621b7577fe86"},{"summary_id":"f9fb516e-33e9-4e5e-a188-27c43109516b","completed_at":"2020-11-05T15:32:03.426Z","set":{"type":"reps","weight":0,"id":"94d753b8-fd28-4882-89c5-b8b53ed80494","reps":12,"estimated_duration":26,"position":7,"duration":20,"intensity":"","distance":0,"is_two_dumbbells":false,"exercise":{"name":"Resistance Band Reverse Fly","type":"","side":"","is_alternating":false,"is_duration":true,"description":"Stand with both feet on the center of the band, hip width apart. Bend at your hips about forty fives degrees. With your elbows slightly bent, pull the bands up and out to your sides","id":"0c380a97-5292-4e26-b238-9f4eb2f42db9","muscle_groups":"Middle Back","is_two_dumbbells":false,"movement_patterns":"Upper Pull","is_reps":true,"is_weight":true}},"started_at":"2020-11-05T15:31:33.886Z","weight":0,"set_id":"94d753b8-fd28-4882-89c5-b8b53ed80494","time_spent_active":30,"id":"591025df-3787-4bae-a0e4-b0418e31db4b"},{"summary_id":"f9fb516e-33e9-4e5e-a188-27c43109516b","id":"616eeb0c-783c-4d37-8743-7fa9c649cbed","weight":45,"set":{"id":"738ce2db-1a31-45b6-9da7-37990a8c181a","exercise":{"name":"Landmine Shoulder Press","is_two_dumbbells":false,"is_weight":true,"type":"","muscle_groups":"Shoulders","id":"f5cb60ae-4643-4896-bb7d-bd301805bcd7","movement_patterns":"Upper Push","is_alternating":false,"is_reps":true,"is_duration":true,"description":"Anchor the barbell in a corner. Place your right knee on the ground and hold the barbell with your right hand. Your left knee should be at ninety degrees. Lift the barbell up and out with your arm fully extended at the top. Slowly lower back down","side":"right_arm"},"reps":8,"type":"reps","duration":30,"distance":0,"estimated_duration":27,"is_two_dumbbells":false,"weight":45,"position":9,"intensity":"weight_lb_45"},"started_at":"2020-11-05T15:13:08.459Z","completed_at":"2020-11-05T15:13:09.794Z","set_id":"738ce2db-1a31-45b6-9da7-37990a8c181a","time_spent_active":2},{"id":"637902a6-69eb-4831-af71-1f33b33572b5","time_spent_active":40,"summary_id":"f9fb516e-33e9-4e5e-a188-27c43109516b","weight":15,"set":{"is_two_dumbbells":true,"id":"0ede78c8-034a-42d5-a4ea-e454b65f3e6e","exercise":{"description":"From a standing position with dumbbells in front of your hips and a slight bend in your elbow. Raise both dumbbells out to the side under control until they get to shoulder height.  Lower back to the starting position.","is_reps":true,"name":"Dumbbell Lateral Shoulder Raises","muscle_groups":"Shoulders","side":"","is_duration":true,"is_two_dumbbells":true,"type":"","is_alternating":false,"id":"601770ea-0011-4c53-8e9f-65a5243ce724","is_weight":true,"movement_patterns":"Upper Push"},"reps":10,"type":"reps","weight":15,"position":6,"distance":0,"intensity":"weight_lb:dumbbells_15","estimated_duration":28,"duration":30},"completed_at":"2020-11-05T15:31:21.872Z","set_id":"0ede78c8-034a-42d5-a4ea-e454b65f3e6e","started_at":"2020-11-05T15:30:42.509Z"},{"completed_at":"2020-11-05T15:04:23.965Z","set":{"position":0,"type":"reps","reps":8,"duration":30,"distance":0,"estimated_duration":27,"intensity":"weight_lb_45","is_two_dumbbells":false,"weight":45,"exercise":{"description":"Anchor the barbell in a corner. Place your left knee on the ground and hold the barbell with your left hand. Your right knee should be at ninety degrees. Lift the barbell up and out with your arm fully extended at the top. Slowly lower back down","side":"left_arm","type":"","is_alternating":false,"is_duration":true,"is_reps":true,"is_two_dumbbells":false,"movement_patterns":"Upper Push","muscle_groups":"Shoulders","id":"305993c7-6825-4661-8ffb-40778b27327d","name":"Landmine Shoulder Press","is_weight":true},"id":"eab32945-a10a-4cfa-8727-400651e971b2"},"weight":45,"id":"63fd2395-7bc6-4026-9d5b-ba87a71e7650","time_spent_active":138,"set_id":"eab32945-a10a-4cfa-8727-400651e971b2","summary_id":"f9fb516e-33e9-4e5e-a188-27c43109516b","started_at":"2020-11-05T15:02:05.994Z"},{"set_id":"df2aef3e-4c1f-449b-8ae0-c706b4de9f1e","started_at":"2020-11-05T15:41:24.087Z","time_spent_active":30,"summary_id":"f9fb516e-33e9-4e5e-a188-27c43109516b","set":{"exercise":{"description":"Sit with your knees out and soles of your feet together.. Keep a tall torso as you lean your chest forward,, and push your knees apart with your elbows. Breathe deeply.","movement_patterns":"Mobility","name":"Butterfly Stretch","side":"","is_two_dumbbells":false,"type":"","is_alternating":false,"id":"5efa3e63-c925-45e6-bfc3-c57531f02c3b","is_reps":false,"is_duration":true,"is_weight":false},"id":"df2aef3e-4c1f-449b-8ae0-c706b4de9f1e","type":"duration","position":2,"weight":0,"reps":0,"estimated_duration":30,"intensity":"","distance":0,"duration":30,"is_two_dumbbells":false},"completed_at":"2020-11-05T15:41:53.548Z","id":"683c819b-c083-44ed-bb9b-d4bf30822482"},{"id":"70c9e1f3-4354-4684-b756-6ed4d60b3a5f","set_id":"c3011022-75cc-40c4-be39-2ba61ad44b84","completed_at":"2020-11-05T15:28:43.353Z","started_at":"2020-11-05T15:28:13.891Z","summary_id":"f9fb516e-33e9-4e5e-a188-27c43109516b","set":{"duration":30,"reps":0,"weight":0,"type":"duration","estimated_duration":30,"distance":0,"id":"c3011022-75cc-40c4-be39-2ba61ad44b84","exercise":{"is_weight":false,"name":"Recover","is_reps":false,"description":"Use this time to catch your breath. It will help you get more out of what's next","is_alternating":false,"is_duration":true,"type":"rest","side":"","is_two_dumbbells":false,"id":"9b983f5f-e229-4d46-9258-e11e430d3a54"},"position":2,"is_two_dumbbells":false},"time_spent_active":30},{"started_at":"2020-11-05T15:08:55.710Z","time_spent_active":26,"id":"7254b72e-07d8-4cbd-a5d0-2664a58782dd","weight":45,"set_id":"2e6892a0-a71e-4187-9663-0ad874895d12","summary_id":"f9fb516e-33e9-4e5e-a188-27c43109516b","completed_at":"2020-11-05T15:09:21.287Z","set":{"estimated_duration":27,"is_two_dumbbells":false,"weight":45,"duration":30,"reps":8,"position":5,"intensity":"weight_lb_45","type":"reps","id":"2e6892a0-a71e-4187-9663-0ad874895d12","distance":0,"exercise":{"is_reps":true,"id":"f5cb60ae-4643-4896-bb7d-bd301805bcd7","type":"","is_two_dumbbells":false,"is_weight":true,"name":"Landmine Shoulder Press","movement_patterns":"Upper Push","is_duration":true,"side":"right_arm","is_alternating":false,"description":"Anchor the barbell in a corner. Place your right knee on the ground and hold the barbell with your right hand. Your left knee should be at ninety degrees. Lift the barbell up and out with your arm fully extended at the top. Slowly lower back down","muscle_groups":"Shoulders"}}},{"started_at":"2020-11-05T15:20:59.548Z","time_spent_active":30,"set_id":"4e3341e0-6301-4280-a732-44b485bfa58f","set":{"weight":0,"type":"duration","reps":0,"exercise":{"description":"Use this time to catch your breath. It will help you get more out of what's next","type":"rest","name":"Recover","is_duration":true,"is_two_dumbbells":false,"side":"","is_weight":false,"is_alternating":false,"id":"9b983f5f-e229-4d46-9258-e11e430d3a54","is_reps":false},"estimated_duration":30,"id":"4e3341e0-6301-4280-a732-44b485bfa58f","position":3,"distance":0,"is_two_dumbbells":false,"duration":30},"id":"7b103c1a-4bf6-4891-a33c-c718977b1474","completed_at":"2020-11-05T15:21:29.010Z","summary_id":"f9fb516e-33e9-4e5e-a188-27c43109516b"},{"set_id":"e0abcb0f-b284-48aa-939b-b23485979be1","started_at":"2020-11-05T15:45:01.409Z","time_spent_active":30,"id":"7f642eff-86c1-42ca-b257-d8ad6090f393","completed_at":"2020-11-05T15:45:30.873Z","summary_id":"f9fb516e-33e9-4e5e-a188-27c43109516b","set":{"id":"e0abcb0f-b284-48aa-939b-b23485979be1","duration":30,"weight":0,"type":"duration","distance":0,"estimated_duration":30,"is_two_dumbbells":false,"intensity":"","reps":0,"exercise":{"is_duration":true,"is_reps":true,"movement_patterns":"Hip Flexion,Upper Pull,Yoga,Mobility","is_weight":false,"type":"","is_two_dumbbells":false,"muscle_groups":"Hamstrings,Ankles,Shoulders,Feet,wrists","is_alternating":false,"id":"67d6b18e-678f-49e6-945a-405506128163","side":"","name":"Downward Facing Dog"},"position":8}},{"set_id":"f4a636c8-fc51-4316-9663-638b50383aad","time_spent_active":60,"summary_id":"f9fb516e-33e9-4e5e-a188-27c43109516b","id":"8d92045d-88d9-411b-aba7-2c759f161fe9","started_at":"2020-11-05T15:06:53.028Z","completed_at":"2020-11-05T15:07:52.491Z","set":{"distance":0,"type":"duration","estimated_duration":60,"is_two_dumbbells":false,"reps":0,"exercise":{"is_two_dumbbells":false,"is_reps":false,"is_alternating":false,"is_duration":true,"name":"Recover","side":"","id":"9b983f5f-e229-4d46-9258-e11e430d3a54","description":"Use this time to catch your breath. It will help you get more out of what's next","type":"rest","is_weight":false},"duration":60,"weight":0,"id":"f4a636c8-fc51-4316-9663-638b50383aad","position":3}},{"time_spent_active":30,"id":"9295a30f-943b-4f19-a0cf-c54e809a68f6","summary_id":"f9fb516e-33e9-4e5e-a188-27c43109516b","set_id":"0dee3eb3-4949-4cb7-9b61-59e75dc17ee3","completed_at":"2020-11-05T15:38:40.821Z","started_at":"2020-11-05T15:38:11.564Z","set":{"estimated_duration":55,"exercise":{"is_reps":true,"is_two_dumbbells":false,"movement_patterns":"Anti-Extension,Anti-Rotation","muscle_groups":"Core,Shoulders,Obliques","name":"High Plank Bird Dog","is_weight":false,"id":"01f5a2bb-ecf7-4168-92b3-35bd78592e26","type":"","side":"","is_duration":true,"is_alternating":true},"intensity":"reps_slow","position":8,"weight":0,"type":"reps","is_two_dumbbells":false,"reps":5,"duration":30,"id":"0dee3eb3-4949-4cb7-9b61-59e75dc17ee3","distance":0}},{"set_id":"4b83c252-0caa-47d1-b93d-fdc79f86e1be","set":{"intensity":"weight_lb:dumbbells_95","is_two_dumbbells":true,"duration":30,"position":4,"reps":8,"id":"4b83c252-0caa-47d1-b93d-fdc79f86e1be","estimated_duration":28,"type":"reps","distance":0,"weight":95,"exercise":{"name":"Dumbbell Bench Press","is_reps":true,"side":"","is_duration":true,"description":"Lay down on your back on a bench and keep your legs at ninety degrees. Keep your black flat on the bench and press the dumbbells up and together","is_two_dumbbells":true,"type":"","is_alternating":false,"movement_patterns":"Upper Push","is_weight":true,"muscle_groups":"Chest,Shoulders","id":"8cc54245-a940-47f3-a5e3-a69338bd068c"}},"summary_id":"f9fb516e-33e9-4e5e-a188-27c43109516b","completed_at":"2020-11-05T15:22:21.370Z","time_spent_active":32,"id":"98ce7cab-4adb-4034-b51d-f12f29f48a2d","weight":95,"started_at":"2020-11-05T15:21:49.458Z"},{"summary_id":"f9fb516e-33e9-4e5e-a188-27c43109516b","completed_at":"2020-11-05T15:46:08.770Z","id":"98f58bd5-db78-477e-bcac-e7657510056e","started_at":"2020-11-05T15:45:39.305Z","set":{"estimated_duration":30,"duration":30,"distance":0,"is_two_dumbbells":false,"id":"2b540afa-8c7d-4fed-8ba5-ad02f14de371","reps":0,"weight":0,"exercise":{"side":"","is_weight":false,"id":"738b8e4a-c124-49db-bdb2-c52edc96f6ae","is_duration":true,"is_reps":false,"type":"","is_two_dumbbells":false,"name":"Seated Forward Fold","is_alternating":false},"type":"duration","position":9,"intensity":""},"set_id":"2b540afa-8c7d-4fed-8ba5-ad02f14de371","time_spent_active":30},{"id":"9ae09f07-85ad-43d3-8c2a-a03005ac5ace","set_id":"84880faf-1b06-4767-b0b9-6edf56b30ca0","time_spent_active":15,"started_at":"2020-11-05T15:13:53.688Z","completed_at":"2020-11-05T15:14:08.155Z","set":{"duration":15,"type":"duration","id":"84880faf-1b06-4767-b0b9-6edf56b30ca0","distance":0,"weight":0,"exercise":{"description":"Use this time to catch your breath. It will help you get more out of what's next","is_alternating":false,"side":"","is_reps":false,"is_two_dumbbells":false,"id":"9b983f5f-e229-4d46-9258-e11e430d3a54","name":"Recover","is_weight":false,"type":"rest","is_duration":true},"reps":0,"estimated_duration":15,"position":11,"is_two_dumbbells":false},"summary_id":"f9fb516e-33e9-4e5e-a188-27c43109516b"},{"summary_id":"f9fb516e-33e9-4e5e-a188-27c43109516b","time_spent_active":30,"id":"a284df70-3fe6-4e04-b3cc-95f234542064","started_at":"2020-11-05T15:35:00.826Z","set_id":"5e861276-0b2d-4ba8-b3dd-e0a19b3e1b01","set":{"exercise":{"type":"rest","description":"Use this time to catch your breath. It will help you get more out of what's next","id":"9b983f5f-e229-4d46-9258-e11e430d3a54","side":"","is_reps":false,"is_alternating":false,"is_duration":true,"is_weight":false,"is_two_dumbbells":false,"name":"Recover"},"weight":0,"reps":0,"duration":30,"id":"5e861276-0b2d-4ba8-b3dd-e0a19b3e1b01","type":"duration","estimated_duration":30,"is_two_dumbbells":false,"distance":0,"position":3},"completed_at":"2020-11-05T15:35:30.282Z"},{"id":"a5e09c86-4674-4e02-8bd9-0869aadf8529","time_spent_active":30,"set_id":"d45da4d8-43f8-4cda-a4cc-cd10e8a0b7a8","started_at":"2020-11-05T15:42:35.873Z","summary_id":"f9fb516e-33e9-4e5e-a188-27c43109516b","completed_at":"2020-11-05T15:43:05.336Z","set":{"id":"d45da4d8-43f8-4cda-a4cc-cd10e8a0b7a8","estimated_duration":30,"duration":30,"reps":0,"intensity":"","is_two_dumbbells":false,"exercise":{"is_reps":false,"side":"right_side","is_alternating":false,"type":"","name":"Pigeon Pose","is_two_dumbbells":false,"muscle_groups":"Glutes,Hips,Pectoralis Major,Shoulders,Rectus Abdominis","id":"35e8a829-b480-4397-81a6-94bb3d03351e","is_duration":true,"is_weight":false,"movement_patterns":"Yoga,Mobility,Hip Extension,Hip External Rotation,Shoulder Flexion"},"position":4,"type":"duration","weight":0,"distance":0}},{"set":{"exercise":{"type":"","is_weight":true,"name":"Face Pull","is_duration":true,"is_reps":true,"muscle_groups":"Shoulders","movement_patterns":"Scapular","description":"Start in an athletic stance,, holding the rope with your hands facing each other.. Keep your elbows high,, and sqeeze them back,, to bring the rope towards your face.. Pause and return under contol..","is_two_dumbbells":false,"id":"08df1103-cdd0-490a-8b9d-e44063f091ac","is_alternating":false,"side":""},"weight":35,"distance":0,"reps":12,"id":"3ace7e35-f7f0-4169-9677-199c1de5f069","estimated_duration":33,"intensity":"weight_lb_35","position":6,"is_two_dumbbells":false,"type":"reps","duration":30},"time_spent_active":52,"started_at":"2020-11-05T15:09:36.303Z","summary_id":"f9fb516e-33e9-4e5e-a188-27c43109516b","weight":35,"set_id":"3ace7e35-f7f0-4169-9677-199c1de5f069","id":"ab9b2316-239d-4de7-995e-05a1332a0a71","completed_at":"2020-11-05T15:10:28.189Z"},{"summary_id":"f9fb516e-33e9-4e5e-a188-27c43109516b","set":{"weight":0,"distance":0,"reps":0,"duration":30,"position":6,"intensity":"","is_two_dumbbells":false,"id":"546422e2-35ab-438b-83c1-5bd2e1549029","type":"duration","exercise":{"is_duration":true,"is_alternating":true,"muscle_groups":"Glutes","is_two_dumbbells":false,"type":"","is_reps":true,"description":"Stand tall and gently pull your knee and ankle up toward your chest, stretching the outside of your hip.","name":"Hip Cradles","is_weight":false,"id":"0713c17c-2d74-4794-b712-1e6987c55e99","side":"","movement_patterns":"Dynamic Flexibility"},"estimated_duration":30},"id":"b4619d41-85fd-4141-8960-5f4183e26fb1","completed_at":"2020-11-05T14:59:44.865Z","started_at":"2020-11-05T14:59:15.402Z","set_id":"546422e2-35ab-438b-83c1-5bd2e1549029","time_spent_active":30},{"id":"b613aee8-d280-429d-8108-dd7d62a8ced7","set":{"duration":30,"id":"c537c7ba-825c-4816-98c8-9dd3a1230eae","reps":0,"type":"duration","exercise":{"is_two_dumbbells":false,"is_duration":true,"id":"9b983f5f-e229-4d46-9258-e11e430d3a54","is_weight":false,"type":"rest","name":"Recover","is_reps":false,"description":"Use this time to catch your breath. It will help you get more out of what's next","is_alternating":false,"side":""},"position":7,"distance":0,"estimated_duration":30,"is_two_dumbbells":false,"weight":0},"completed_at":"2020-11-05T15:38:03.127Z","time_spent_active":30,"summary_id":"f9fb516e-33e9-4e5e-a188-27c43109516b","set_id":"c537c7ba-825c-4816-98c8-9dd3a1230eae","started_at":"2020-11-05T15:37:33.665Z"},{"started_at":"2020-11-05T15:01:01.114Z","completed_at":"2020-11-05T15:01:30.573Z","id":"b8b929bb-1c11-40de-b1ac-dae10376f311","set_id":"20a02182-051c-4f2d-85e8-f94235589ace","time_spent_active":30,"summary_id":"f9fb516e-33e9-4e5e-a188-27c43109516b","set":{"estimated_duration":30,"position":9,"type":"duration","exercise":{"description":"Use this time to catch your breath. It will help you get more out of what's next","type":"rest","is_duration":true,"is_two_dumbbells":false,"is_alternating":false,"is_reps":false,"is_weight":false,"name":"Recover","id":"9b983f5f-e229-4d46-9258-e11e430d3a54","side":""},"distance":0,"intensity":"","id":"20a02182-051c-4f2d-85e8-f94235589ace","is_two_dumbbells":false,"reps":0,"duration":30,"weight":0}},{"set_id":"923a99de-e938-4c60-9303-cecda2d0a722","id":"b96aa7c3-c6b2-43ac-9c83-1381318ba728","started_at":"2020-11-05T15:10:28.208Z","set":{"reps":0,"weight":0,"type":"duration","distance":0,"position":7,"is_two_dumbbells":false,"id":"923a99de-e938-4c60-9303-cecda2d0a722","duration":60,"exercise":{"type":"rest","is_two_dumbbells":false,"is_alternating":false,"is_reps":false,"description":"Use this time to catch your breath. It will help you get more out of what's next","side":"","is_weight":false,"name":"Recover","is_duration":true,"id":"9b983f5f-e229-4d46-9258-e11e430d3a54"},"estimated_duration":60},"time_spent_active":60,"completed_at":"2020-11-05T15:11:27.671Z","summary_id":"f9fb516e-33e9-4e5e-a188-27c43109516b"},{"started_at":"2020-11-05T15:24:44.094Z","id":"c344ce92-c2e9-45bd-bf61-6a86ff0d6110","set":{"intensity":"weight_lb:dumbbells_15","duration":30,"is_two_dumbbells":true,"type":"reps","exercise":{"is_duration":true,"side":"","is_weight":true,"description":"From a standing position with dumbbells in front of your hips and a slight bend in your elbow. Raise both dumbbells out to the side under control until they get to shoulder height.  Lower back to the starting position.","is_reps":true,"muscle_groups":"Shoulders","is_alternating":false,"name":"Dumbbell Lateral Shoulder Raises","id":"601770ea-0011-4c53-8e9f-65a5243ce724","movement_patterns":"Upper Push","type":"","is_two_dumbbells":true},"estimated_duration":28,"id":"c0009cfa-59ec-4821-bf7c-bc8f3903a27f","position":0,"distance":0,"reps":10,"weight":15},"set_id":"c0009cfa-59ec-4821-bf7c-bc8f3903a27f","completed_at":"2020-11-05T15:27:24.184Z","summary_id":"f9fb516e-33e9-4e5e-a188-27c43109516b","time_spent_active":161,"weight":15},{"set":{"reps":0,"type":"duration","id":"95750447-e0f3-457c-aa5c-be86efab078b","is_two_dumbbells":false,"weight":0,"position":7,"exercise":{"is_duration":true,"side":"","id":"9b983f5f-e229-4d46-9258-e11e430d3a54","description":"Use this time to catch your breath. It will help you get more out of what's next","is_reps":false,"is_weight":false,"name":"Recover","type":"rest","is_two_dumbbells":false,"is_alternating":false},"estimated_duration":30,"duration":30,"distance":0},"summary_id":"f9fb516e-33e9-4e5e-a188-27c43109516b","set_id":"95750447-e0f3-457c-aa5c-be86efab078b","started_at":"2020-11-05T15:24:04.186Z","time_spent_active":30,"completed_at":"2020-11-05T15:24:33.650Z","id":"c7334745-24b5-4f9c-8979-359f6f0496bf"},{"set_id":"0701dfd2-f9b1-456e-b66b-a1d324c4b59c","started_at":"2020-11-05T14:57:25.693Z","summary_id":"f9fb516e-33e9-4e5e-a188-27c43109516b","time_spent_active":30,"id":"c7481fe7-26b9-4ffb-95c3-08ec846ce64b","set":{"type":"duration","position":3,"estimated_duration":30,"is_two_dumbbells":false,"reps":0,"weight":0,"id":"0701dfd2-f9b1-456e-b66b-a1d324c4b59c","intensity":"","duration":30,"distance":0,"exercise":{"is_weight":false,"muscle_groups":"Quads,Glutes","is_duration":true,"movement_patterns":"Mobility","id":"ff9b5d30-0a51-422a-80c5-3ff13384fd3f","name":"Reverse Lunge Reaches","is_alternating":true,"is_two_dumbbells":false,"side":"","description":"Step back and drop down with your knee hovering just above the ground.  On the side that stepped back, reach your arm up to the ceiling.","type":"","is_reps":true}},"completed_at":"2020-11-05T14:57:55.153Z"},{"set":{"weight":35,"estimated_duration":33,"id":"5632f29b-5401-4a6d-8ce8-9b1ce537bd24","intensity":"weight_lb_35","distance":0,"is_two_dumbbells":false,"reps":12,"duration":30,"position":10,"exercise":{"name":"Face Pull","side":"","description":"Start in an athletic stance,, holding the rope with your hands facing each other.. Keep your elbows high,, and sqeeze them back,, to bring the rope towards your face.. Pause and return under contol..","type":"","is_alternating":false,"is_reps":true,"muscle_groups":"Shoulders","movement_patterns":"Scapular","is_duration":true,"is_two_dumbbells":false,"id":"08df1103-cdd0-490a-8b9d-e44063f091ac","is_weight":true},"type":"reps"},"time_spent_active":29,"started_at":"2020-11-05T15:13:24.807Z","set_id":"5632f29b-5401-4a6d-8ce8-9b1ce537bd24","completed_at":"2020-11-05T15:13:53.665Z","summary_id":"f9fb516e-33e9-4e5e-a188-27c43109516b","id":"c84c7257-4851-494f-8677-056fb0a3fb7a","weight":35},{"started_at":"2020-11-05T15:43:45.619Z","time_spent_active":30,"set_id":"c8e0107f-3f29-4e47-bfb6-1feda0e17e77","completed_at":"2020-11-05T15:44:15.083Z","summary_id":"f9fb516e-33e9-4e5e-a188-27c43109516b","set":{"exercise":{"name":"Crossbody Lat Stretch","is_two_dumbbells":false,"is_reps":false,"movement_patterns":"Mobility","side":"right_arm","type":"","id":"9fa82722-c5b1-48a4-8dc6-baca2d1b8c41","is_weight":false,"is_duration":true,"muscle_groups":"Middle Back","is_alternating":false,"description":"Starting in a child's pose sitting back on your heels, reach your right arm across your body and place the back of your palm on the floor.  Lock that hand down with your left hand, sit back and feel the stretch down your right side."},"position":6,"reps":0,"duration":30,"distance":0,"intensity":"","weight":0,"type":"duration","estimated_duration":30,"is_two_dumbbells":false,"id":"c8e0107f-3f29-4e47-bfb6-1feda0e17e77"},"id":"c88b1ea7-d636-4d67-9c80-a4764380eb19"},{"set_id":"7fd235b8-0455-4a42-912e-f3d5d9ec0ba1","time_spent_active":64,"weight":45,"set":{"exercise":{"id":"305993c7-6825-4661-8ffb-40778b27327d","name":"Landmine Shoulder Press","type":"","is_alternating":false,"is_reps":true,"is_duration":true,"description":"Anchor the barbell in a corner. Place your left knee on the ground and hold the barbell with your left hand. Your right knee should be at ninety degrees. Lift the barbell up and out with your arm fully extended at the top. Slowly lower back down","is_weight":true,"muscle_groups":"Shoulders","movement_patterns":"Upper Push","side":"left_arm","is_two_dumbbells":false},"estimated_duration":27,"intensity":"weight_lb_45","reps":8,"weight":45,"type":"reps","duration":30,"id":"7fd235b8-0455-4a42-912e-f3d5d9ec0ba1","distance":0,"is_two_dumbbells":false,"position":8},"started_at":"2020-11-05T15:12:03.079Z","id":"c99947db-86a7-4423-ad46-5fe15695edf9","completed_at":"2020-11-05T15:13:06.535Z","summary_id":"f9fb516e-33e9-4e5e-a188-27c43109516b"},{"set":{"weight":0,"id":"55e2c18d-e8a5-4f93-857a-c0b5da5b0e79","is_two_dumbbells":false,"estimated_duration":30,"reps":0,"duration":30,"type":"duration","distance":0,"exercise":{"is_weight":false,"side":"","name":"Recover","id":"9b983f5f-e229-4d46-9258-e11e430d3a54","is_alternating":false,"type":"rest","is_two_dumbbells":false,"is_reps":false,"description":"Use this time to catch your breath. It will help you get more out of what's next","is_duration":true},"position":5},"set_id":"55e2c18d-e8a5-4f93-857a-c0b5da5b0e79","time_spent_active":30,"id":"d415224c-9110-4c1d-9918-d19c3a92ddb7","completed_at":"2020-11-05T15:22:50.851Z","started_at":"2020-11-05T15:22:21.388Z","summary_id":"f9fb516e-33e9-4e5e-a188-27c43109516b"},{"time_spent_active":30,"completed_at":"2020-11-05T15:47:24.565Z","set_id":"2708bafe-7796-4abe-9d17-202422a99df6","summary_id":"f9fb516e-33e9-4e5e-a188-27c43109516b","id":"d4929620-b25a-4826-903d-69332ff1e6c7","started_at":"2020-11-05T15:46:55.111Z","set":{"distance":0,"weight":0,"estimated_duration":30,"is_two_dumbbells":false,"id":"2708bafe-7796-4abe-9d17-202422a99df6","duration":30,"exercise":{"is_alternating":false,"is_weight":false,"name":"Figure Four Stretch","movement_patterns":"Mobility","side":"right_leg","is_reps":false,"is_duration":true,"id":"2634a71d-885c-4fcc-83b7-5ec4fa5978db","description":"Put your right ankle against your left knee.  Use both hands to pull your legs back toward you.  Focus on rotating your right knee out to feel a greater stretch on the lateral hip.","muscle_groups":"Glutes","type":"","is_two_dumbbells":false},"intensity":"","type":"duration","reps":0,"position":11}},{"completed_at":"2020-11-05T15:40:04.273Z","time_spent_active":6,"set":{"id":"4864a7ed-cffc-403a-9577-7090ed6bd520","position":11,"estimated_duration":30,"is_two_dumbbells":false,"type":"duration","weight":0,"reps":0,"duration":30,"exercise":{"is_alternating":false,"is_weight":false,"name":"Recover","is_reps":false,"side":"","is_two_dumbbells":false,"id":"9b983f5f-e229-4d46-9258-e11e430d3a54","description":"Use this time to catch your breath. It will help you get more out of what's next","is_duration":true,"type":"rest"},"distance":0},"id":"d5993e0c-d5a3-4a51-a379-46e65f34bd39","started_at":"2020-11-05T15:39:58.413Z","summary_id":"f9fb516e-33e9-4e5e-a188-27c43109516b","set_id":"4864a7ed-cffc-403a-9577-7090ed6bd520"},{"set":{"reps":12,"exercise":{"name":"Resistance Band Reverse Fly","is_duration":true,"is_reps":true,"is_alternating":false,"id":"0c380a97-5292-4e26-b238-9f4eb2f42db9","description":"Stand with both feet on the center of the band, hip width apart. Bend at your hips about forty fives degrees. With your elbows slightly bent, pull the bands up and out to your sides","is_two_dumbbells":false,"is_weight":true,"side":"","type":"","movement_patterns":"Upper Pull","muscle_groups":"Middle Back"},"distance":0,"type":"reps","weight":0,"duration":20,"id":"65c3948e-9a5e-4d4c-b82a-013f667f7829","intensity":"","is_two_dumbbells":false,"position":4,"estimated_duration":26},"completed_at":"2020-11-05T15:30:02.625Z","started_at":"2020-11-05T15:29:37.760Z","summary_id":"f9fb516e-33e9-4e5e-a188-27c43109516b","id":"d7716f85-297a-423d-9025-b0ad04cade1b","weight":0,"time_spent_active":25,"set_id":"65c3948e-9a5e-4d4c-b82a-013f667f7829"},{"set_id":"f1ccbe9e-652f-4a4f-b2ba-e17c5e41c164","id":"d8030e54-3d02-4261-a81a-fbf4a0cbca22","time_spent_active":30,"set":{"weight":0,"type":"duration","distance":0,"exercise":{"is_two_dumbbells":false,"name":"Pigeon Pose","type":"","is_weight":false,"muscle_groups":"Glutes,Hips,Pectoralis Major,Shoulders,Rectus Abdominis","is_reps":false,"movement_patterns":"Yoga,Mobility,Hip Extension,Hip External Rotation,Shoulder Flexion","id":"eae3ed58-1af8-4ad5-94d3-75a800fc5ab7","is_duration":true,"is_alternating":false,"side":"left_side"},"reps":0,"position":3,"intensity":"","is_two_dumbbells":false,"duration":30,"id":"f1ccbe9e-652f-4a4f-b2ba-e17c5e41c164","estimated_duration":30},"completed_at":"2020-11-05T15:42:31.437Z","started_at":"2020-11-05T15:42:01.974Z","summary_id":"f9fb516e-33e9-4e5e-a188-27c43109516b"},{"completed_at":"2020-11-05T15:33:06.957Z","id":"dacac705-dc65-45be-bfb5-a3098f6e6a83","time_spent_active":26,"set_id":"83ff2842-51d5-4eec-a279-203e236a233e","started_at":"2020-11-05T15:32:41.335Z","summary_id":"f9fb516e-33e9-4e5e-a188-27c43109516b","set":{"exercise":{"muscle_groups":"Core,Shoulders,Obliques","is_reps":true,"side":"","is_two_dumbbells":false,"is_duration":true,"is_weight":false,"movement_patterns":"Anti-Extension,Anti-Rotation","is_alternating":true,"type":"","name":"High Plank Bird Dog","id":"01f5a2bb-ecf7-4168-92b3-35bd78592e26"},"intensity":"reps_slow","duration":30,"weight":0,"position":0,"estimated_duration":55,"distance":0,"type":"reps","is_two_dumbbells":false,"id":"83ff2842-51d5-4eec-a279-203e236a233e","reps":5}},{"set":{"duration":30,"intensity":"","weight":0,"reps":0,"estimated_duration":30,"exercise":{"is_duration":true,"id":"dbd273ea-46a9-4637-9586-c22056a63caa","is_reps":true,"muscle_groups":"Hamstrings","is_weight":false,"type":"","is_two_dumbbells":false,"side":"","movement_patterns":"Dynamic Flexibility","name":"Dynamic Hamstring Stretch","is_alternating":true,"description":"Plant your heel and trigger your toes up.  Keeping your leg straight and back flat, sweep your arms through.  Switch legs while maintaining smooth form."},"id":"b679aa06-de53-463c-a177-6279eb84bd77","position":8,"distance":0,"is_two_dumbbells":false,"type":"duration"},"time_spent_active":30,"summary_id":"f9fb516e-33e9-4e5e-a188-27c43109516b","started_at":"2020-11-05T15:00:31.189Z","completed_at":"2020-11-05T15:01:00.652Z","id":"e252901a-8d92-4416-b1d1-29fcafa95cc4","set_id":"b679aa06-de53-463c-a177-6279eb84bd77"},{"set_id":"70b01685-3694-42ef-8bb3-aa2d9fb63b21","started_at":"2020-11-05T15:14:28.564Z","completed_at":"2020-11-05T15:18:15.314Z","time_spent_active":227,"id":"e3d0f367-08d4-47e1-b986-bfda4f57c885","weight":70,"summary_id":"f9fb516e-33e9-4e5e-a188-27c43109516b","set":{"position":0,"estimated_duration":28,"intensity":"weight_lb:dumbbells_70","exercise":{"side":"","is_duration":true,"muscle_groups":"Chest,Shoulders","is_two_dumbbells":true,"is_weight":true,"is_reps":true,"is_alternating":false,"type":"","description":"Lay down on your back on a bench and keep your legs at ninety degrees. Keep your black flat on the bench and press the dumbbells up and together","movement_patterns":"Upper Push","id":"8cc54245-a940-47f3-a5e3-a69338bd068c","name":"Dumbbell Bench Press"},"type":"reps","is_two_dumbbells":true,"weight":70,"distance":0,"duration":30,"reps":8,"id":"70b01685-3694-42ef-8bb3-aa2d9fb63b21"}},{"time_spent_active":53,"completed_at":"2020-11-05T15:24:04.159Z","started_at":"2020-11-05T15:23:11.296Z","id":"e3f84cd4-de52-4a78-a160-a9166b1f9d88","set_id":"9790f3fb-2cc6-456c-904d-a5dd1e0e8dbf","summary_id":"f9fb516e-33e9-4e5e-a188-27c43109516b","weight":95,"set":{"type":"reps","duration":30,"intensity":"weight_lb:dumbbells_95","position":6,"weight":95,"id":"9790f3fb-2cc6-456c-904d-a5dd1e0e8dbf","reps":8,"distance":0,"is_two_dumbbells":true,"exercise":{"id":"8cc54245-a940-47f3-a5e3-a69338bd068c","movement_patterns":"Upper Push","muscle_groups":"Chest,Shoulders","name":"Dumbbell Bench Press","is_duration":true,"side":"","type":"","description":"Lay down on your back on a bench and keep your legs at ninety degrees. Keep your black flat on the bench and press the dumbbells up and together","is_reps":true,"is_alternating":false,"is_two_dumbbells":true,"is_weight":true},"estimated_duration":28}},{"id":"eb9e2acb-f3f4-4d0f-a9b3-37e4c32c6ecc","time_spent_active":30,"set_id":"4259a93a-b357-4cb7-8624-f2852a2c7bc7","completed_at":"2020-11-05T15:30:32.099Z","summary_id":"f9fb516e-33e9-4e5e-a188-27c43109516b","set":{"duration":30,"is_two_dumbbells":false,"reps":0,"type":"duration","distance":0,"id":"4259a93a-b357-4cb7-8624-f2852a2c7bc7","position":5,"estimated_duration":30,"weight":0,"exercise":{"id":"9b983f5f-e229-4d46-9258-e11e430d3a54","description":"Use this time to catch your breath. It will help you get more out of what's next","is_alternating":false,"is_weight":false,"side":"","is_reps":false,"is_duration":true,"name":"Recover","is_two_dumbbells":false,"type":"rest"}},"started_at":"2020-11-05T15:30:02.636Z"},{"id":"f322c67d-1751-4155-99d6-e7cc9ad4ab39","time_spent_active":1,"completed_at":"2020-11-05T15:35:00.805Z","started_at":"2020-11-05T15:35:00.195Z","summary_id":"f9fb516e-33e9-4e5e-a188-27c43109516b","weight":0,"set":{"type":"reps","duration":30,"distance":0,"is_two_dumbbells":false,"position":2,"id":"eb4ae71c-c43b-46d5-8932-2ca852b36b71","reps":12,"weight":0,"exercise":{"is_reps":true,"id":"f1b239c8-6f3d-4bcc-b562-2dcaa3a17c0a","is_two_dumbbells":false,"movement_patterns":"Core,Rotational","description":"Start with your right knee down,, and left side facing the cable column.. Stay tall as you bring the rope in and across your body.. Finish with your arms straight,, and hands outside your right hip..","type":"","is_duration":true,"is_alternating":false,"muscle_groups":"Abs,Obliques","name":"Split Rope Chop","is_weight":true,"side":"right_side"},"estimated_duration":38},"set_id":"eb4ae71c-c43b-46d5-8932-2ca852b36b71"},{"summary_id":"f9fb516e-33e9-4e5e-a188-27c43109516b","started_at":"2020-11-05T15:40:12.286Z","completed_at":"2020-11-05T15:40:41.758Z","time_spent_active":30,"id":"f65ee0e6-9017-4ab3-9232-e031dcbf7e4d","set_id":"153a986d-6935-4f11-9f0d-932e3b4455cb","set":{"id":"153a986d-6935-4f11-9f0d-932e3b4455cb","position":0,"duration":30,"reps":0,"weight":0,"type":"duration","exercise":{"is_reps":false,"name":"Kneeling Quadriceps Stretch","side":"left_leg","type":"","description":"Kneel on the floor with your right leg forward and left leg back.  With perfect posture, press your hips forward until your feel a stretch in the front of your left thigh.","muscle_groups":"Quads","is_duration":true,"is_two_dumbbells":false,"movement_patterns":"Mobility","is_alternating":false,"is_weight":false,"id":"ec72fd44-505d-4146-ba4d-3386b164cf76"},"distance":0,"estimated_duration":30,"is_two_dumbbells":false,"intensity":""}},{"set_id":"f1d59410-3859-4854-9fb1-57d69f0361b0","summary_id":"f9fb516e-33e9-4e5e-a188-27c43109516b","time_spent_active":115,"started_at":"2020-11-05T15:19:05.265Z","id":"f76b6d90-33ca-467b-9841-edb7628f666f","set":{"reps":8,"duration":30,"weight":95,"is_two_dumbbells":true,"intensity":"weight_lb:dumbbells_95","exercise":{"is_duration":true,"is_weight":true,"is_alternating":false,"name":"Dumbbell Bench Press","side":"","type":"","id":"8cc54245-a940-47f3-a5e3-a69338bd068c","is_two_dumbbells":true,"is_reps":true,"description":"Lay down on your back on a bench and keep your legs at ninety degrees. Keep your black flat on the bench and press the dumbbells up and together","movement_patterns":"Upper Push","muscle_groups":"Chest,Shoulders"},"id":"f1d59410-3859-4854-9fb1-57d69f0361b0","type":"reps","position":2,"distance":0,"estimated_duration":28},"completed_at":"2020-11-05T15:20:59.532Z","weight":95}],"basal_energy_burned":93,"active_energy_burned":380,"started_at":"2020-11-05T14:55:27.966Z","actual_duration":3118}